README.md
setup.py
IDAT/__init__.py
IDAT/anno.py
IDAT/canvas.py
IDAT/default.yaml
IDAT/icon_rc.py
IDAT/main.py
IDAT/rect.py
IDAT/ui/__init__.py
IDAT/ui/about_dialog.py
IDAT/ui/add_annotation_dialog.py
IDAT/ui/choice_label_dialog.py
IDAT/ui/en.ts
IDAT/ui/main_window.py
IDAT/ui/setting_dialog.py
IDAT/ui/shourcut_dialog.py
IDAT/ui/zh_CN.qm
IDAT/ui/zh_CN.ts
IDAT/utils/__init__.py
IDAT/utils/file_ops.py
idat.egg-info/PKG-INFO
idat.egg-info/SOURCES.txt
idat.egg-info/dependency_links.txt
idat.egg-info/entry_points.txt
idat.egg-info/requires.txt
idat.egg-info/top_level.txt