Metadata-Version: 2.1
Name: idat
Version: 1.0.0
Summary: Object Detection Annotation Tool.
Home-page: https://github.com/yatengLG/IDAT
Author: yatengLG
Author-email: yatenglg@qq.com
License: MIT Licence
Keywords: pip,idat,object detection
Platform: any
Classifier: Intended Audience :: Developers
Classifier: Intended Audience :: Science/Research
Classifier: Development Status :: 5 - Production/Stable
Classifier: Natural Language :: Chinese (Simplified)
Classifier: Natural Language :: English
Classifier: License :: OSI Approved :: Apache Software License
Classifier: Operating System :: OS Independent
Classifier: Programming Language :: Python :: 3
Requires-Python: >=3.6
Requires-Dist: imgviz
Requires-Dist: pyqt5
Requires-Dist: pyyaml
